mamba_gator/__init__.py
mamba_gator/__main__.py
mamba_gator/_version.py
mamba_gator/envmanager.py
mamba_gator/handlers.py
mamba_gator/log.py
mamba_gator/rest_api.yml
mamba_gator/labextension/package.json
mamba_gator/labextension/schemas/@mamba-org/gator-lab/package.json.orig
mamba_gator/labextension/schemas/@mamba-org/gator-lab/plugin.json
mamba_gator/labextension/static/230.50210d2bae2c83b03f3c.js
mamba_gator/labextension/static/615.991b324feb8dad5e474f.js
mamba_gator/labextension/static/615.991b324feb8dad5e474f.js.LICENSE.txt
mamba_gator/labextension/static/658.cf2479573cd195139436.js
mamba_gator/labextension/static/722.0515524a6a10cd00116a.js
mamba_gator/labextension/static/837.2b8c8f6b48e4415deef9.js
mamba_gator/labextension/static/remoteEntry.e5cbc08c70b4bb631087.js
mamba_gator/labextension/static/style.js
mamba_gator/labextension/static/third-party-licenses.json
mamba_gator/navigator/README.md
mamba_gator/navigator/__init__.py
mamba_gator/navigator/index.html
mamba_gator/navigator/main.py
mamba_gator/navigator/static/373c04fd2418f5c77eea49d514731058f1907a94ff3b4e5d7c3e5767e8b53d8b.eot
mamba_gator/navigator/static/3f6d3488cf65374f6f676c315340b0ac2be832bd55240c809448e36ef9b96326.woff
mamba_gator/navigator/static/79d088064beb3826054fb88165416235897a856ca952fca1498b1c59b16aaa48.eot
mamba_gator/navigator/static/8ea8791754915a898a3100e63e32978a6d1763be6df8e73a39d3a90d691cdeef.woff2
mamba_gator/navigator/static/9674eb1bd5504717903837093a67668ea88f2ed006d91367d0d4b7aa1f9211fc.svg
mamba_gator/navigator/static/9834b82ad26e2a37583d22676a12dd2eb0fe7c80356a2114d0db1aa8b3899537.woff2
mamba_gator/navigator/static/a3b9817780214caf01e8aec20bcdc2305a1ff34a15fae81ecd0923df9cd5cd0a.svg
mamba_gator/navigator/static/af6397503fcefbd613976c21ad5c1e37298c18bbe07d096db03ccd3af6e05ba8.ttf
mamba_gator/navigator/static/be0a084962d8066884f7fe9bd27ec16e51f5a93b72a502c92c5a24dc87eb2ebc.svg
mamba_gator/navigator/static/bundle.js
mamba_gator/navigator/static/bundle.js.LICENSE.txt
mamba_gator-6.1.0.dist-info/METADATA
mamba_gator-6.1.0.dist-info/WHEEL
mamba_gator-6.1.0.dist-info/entry_points.txt
mamba_gator-6.1.0.dist-info/licenses/LICENSE
mamba_gator-6.1.0.dist-info/RECORD
