Metadata-Version: 2.4
Name: mamba_gator
Version: 6.1.0
Summary: Manage your conda environments
Author: Continuum Analytics, Jupyter Development Team
License: Copyright (c) 2016 Continuum Analytics, Inc. and contributors
License-File: LICENSE
Classifier: Framework :: Jupyter
Classifier: Framework :: Jupyter :: JupyterLab
Classifier: Framework :: Jupyter :: JupyterLab :: 4
Classifier: Framework :: Jupyter :: JupyterLab :: Extensions
Classifier: Framework :: Jupyter :: JupyterLab :: Extensions :: Prebuilt
Classifier: License :: OSI Approved :: BSD License
Classifier: Programming Language :: Python
Classifier: Programming Language :: Python :: 3
Classifier: Programming Language :: Python :: 3.10
Classifier: Programming Language :: Python :: 3.11
Classifier: Programming Language :: Python :: 3.12
Classifier: Programming Language :: Python :: 3.13
Classifier: Programming Language :: Python :: 3.14
Requires-Dist: jupyter-client
Requires-Dist: jupyter-server<3.0.0,>=2.0.0
Requires-Dist: jupyterlab-server<3.0.0,>=2.0.0
Requires-Dist: jupyterlab<5.0.0,>=4.0.0
Requires-Dist: packaging
Requires-Dist: pip
Requires-Dist: tornado
Requires-Dist: traitlets
Provides-Extra: dev
Requires-Dist: hatch; extra == 'dev'
Provides-Extra: docs
Requires-Dist: linkify-it-py; extra == 'docs'
Requires-Dist: myst-parser; extra == 'docs'
Requires-Dist: sphinx; extra == 'docs'
Requires-Dist: sphinx-book-theme; extra == 'docs'
Requires-Dist: sphinx-design; extra == 'docs'
Provides-Extra: test
Requires-Dist: coverage; extra == 'test'
Requires-Dist: flake8; extra == 'test'
Requires-Dist: pytest; extra == 'test'
Requires-Dist: pytest-jupyter[server]>=0.11.0; extra == 'test'
